aliyunsdkeais/__init__.py
aliyunsdkeais/endpoint.py
aliyunsdkeais/request/__init__.py
aliyunsdkeais/request/v20190624/AttachEaiRequest.py
aliyunsdkeais/request/v20190624/AttachEaisEiRequest.py
aliyunsdkeais/request/v20190624/ChangeResourceGroupRequest.py
aliyunsdkeais/request/v20190624/CreateEaiEciRequest.py
aliyunsdkeais/request/v20190624/CreateEaiEcsRequest.py
aliyunsdkeais/request/v20190624/CreateEaiJupyterRequest.py
aliyunsdkeais/request/v20190624/CreateEaiRequest.py
aliyunsdkeais/request/v20190624/CreateEaisEiRequest.py
aliyunsdkeais/request/v20190624/DeleteEaiAllRequest.py
aliyunsdkeais/request/v20190624/DeleteEaiRequest.py
aliyunsdkeais/request/v20190624/DeleteEaisEiRequest.py
aliyunsdkeais/request/v20190624/DescribeEaisRequest.py
aliyunsdkeais/request/v20190624/DescribeRegionsRequest.py
aliyunsdkeais/request/v20190624/DetachEaiRequest.py
aliyunsdkeais/request/v20190624/DetachEaisEiRequest.py
aliyunsdkeais/request/v20190624/GetInstanceMetricsRequest.py
aliyunsdkeais/request/v20190624/ListTagResourcesRequest.py
aliyunsdkeais/request/v20190624/StartEaiJupyterRequest.py
aliyunsdkeais/request/v20190624/StartEaisEiRequest.py
aliyunsdkeais/request/v20190624/StopEaiJupyterRequest.py
aliyunsdkeais/request/v20190624/StopEaisEiRequest.py
aliyunsdkeais/request/v20190624/TagResourcesRequest.py
aliyunsdkeais/request/v20190624/UntagResourcesRequest.py
aliyunsdkeais/request/v20190624/__init__.py
aliyun_python_sdk_eais-2.1.7.dist-info/LICENSE
aliyun_python_sdk_eais-2.1.7.dist-info/METADATA
aliyun_python_sdk_eais-2.1.7.dist-info/WHEEL
aliyun_python_sdk_eais-2.1.7.dist-info/top_level.txt
aliyun_python_sdk_eais-2.1.7.dist-info/RECORD
